<?xml version='1.0' encoding='utf-8'?>
<CarsInSouthAfrica><Car brand="Toyota"><Model><Name>Toyota Hilux</Name><FuelTankCapacity unit="litres">77</FuelTankCapacity></Model><Model><Name>Toyota Corolla Cross</Name><FuelTankCapacity unit="litres">87</FuelTankCapacity></Model><Model><Name>Toyota Corolla Quest</Name><FuelTankCapacity unit="litres">62</FuelTankCapacity></Model><Model><Name>Toyota Starlet</Name><FuelTankCapacity unit="litres">79</FuelTankCapacity></Model><Model><Name>Toyota Fortuner</Name><FuelTankCapacity unit="litres">79</FuelTankCapacity></Model><Model><Name>Toyota Urban Cruiser</Name><FuelTankCapacity unit="litres">65</FuelTankCapacity></Model><Model><Name>Toyota Land Cruiser Prado</Name><FuelTankCapacity unit="litres">87</FuelTankCapacity></Model><Model><Name>Toyota RAV4</Name><FuelTankCapacity unit="litres">43</FuelTankCapacity></Model><Model><Name>Toyota Yaris</Name><FuelTankCapacity unit="litres">70</FuelTankCapacity></Model><Model><Name>Toyota Quantum</Name><FuelTankCapacity unit="litres">83</FuelTankCapacity></Model></Car><Car brand="Volkswagen"><Model><Name>Volkswagen Polo Vivo</Name><FuelTankCapacity unit="litres">51</FuelTankCapacity></Model><Model><Name>Volkswagen Golf GTI</Name><FuelTankCapacity unit="litres">42</FuelTankCapacity></Model><Model><Name>Volkswagen T-Cross</Name><FuelTankCapacity unit="litres">45</FuelTankCapacity></Model><Model><Name>Volkswagen Tiguan</Name><FuelTankCapacity unit="litres">76</FuelTankCapacity></Model><Model><Name>Volkswagen Amarok</Name><FuelTankCapacity unit="litres">89</FuelTankCapacity></Model><Model><Name>Volkswagen Touareg</Name><FuelTankCapacity unit="litres">53</FuelTankCapacity></Model><Model><Name>Volkswagen Polo</Name><FuelTankCapacity unit="litres">37</FuelTankCapacity></Model><Model><Name>Volkswagen Arteon</Name><FuelTankCapacity unit="litres">38</FuelTankCapacity></Model><Model><Name>Volkswagen Caddy</Name><FuelTankCapacity unit="litres">57</FuelTankCapacity></Model><Model><Name>Volkswagen ID.4</Name><FuelTankCapacity unit="litres">47</FuelTankCapacity></Model></Car><Car brand="Ford"><Model><Name>Ford Ranger</Name><FuelTankCapacity unit="litres">36</FuelTankCapacity></Model><Model><Name>Ford EcoSport</Name><FuelTankCapacity unit="litres">45</FuelTankCapacity></Model><Model><Name>Ford Everest</Name><FuelTankCapacity unit="litres">37</FuelTankCapacity></Model><Model><Name>Ford Fiesta</Name><FuelTankCapacity unit="litres">58</FuelTankCapacity></Model><Model><Name>Ford Focus</Name><FuelTankCapacity unit="litres">42</FuelTankCapacity></Model><Model><Name>Ford Mustang</Name><FuelTankCapacity unit="litres">87</FuelTankCapacity></Model><Model><Name>Ford Territory</Name><FuelTankCapacity unit="litres">79</FuelTankCapacity></Model><Model><Name>Ford Tourneo</Name><FuelTankCapacity unit="litres">54</FuelTankCapacity></Model><Model><Name>Ford Transit</Name><FuelTankCapacity unit="litres">53</FuelTankCapacity></Model><Model><Name>Ford Kuga</Name><FuelTankCapacity unit="litres">63</FuelTankCapacity></Model></Car><Car brand="Suzuki"><Model><Name>Suzuki Swift</Name><FuelTankCapacity unit="litres">56</FuelTankCapacity></Model><Model><Name>Suzuki Celerio</Name><FuelTankCapacity unit="litres">39</FuelTankCapacity></Model><Model><Name>Suzuki S-Presso</Name><FuelTankCapacity unit="litres">85</FuelTankCapacity></Model><Model><Name>Suzuki Dzire</Name><FuelTankCapacity unit="litres">72</FuelTankCapacity></Model><Model><Name>Suzuki Baleno</Name><FuelTankCapacity unit="litres">43</FuelTankCapacity></Model><Model><Name>Suzuki Ignis</Name><FuelTankCapacity unit="litres">72</FuelTankCapacity></Model><Model><Name>Suzuki Vitara</Name><FuelTankCapacity unit="litres">50</FuelTankCapacity></Model><Model><Name>Suzuki Jimny</Name><FuelTankCapacity unit="litres">64</FuelTankCapacity></Model><Model><Name>Suzuki Grand Vitara</Name><FuelTankCapacity unit="litres">63</FuelTankCapacity></Model><Model><Name>Suzuki XL6</Name><FuelTankCapacity unit="litres">39</FuelTankCapacity></Model></Car><Car brand="Hyundai"><Model><Name>Hyundai i10</Name><FuelTankCapacity unit="litres">41</FuelTankCapacity></Model><Model><Name>Hyundai i20</Name><FuelTankCapacity unit="litres">57</FuelTankCapacity></Model><Model><Name>Hyundai i30</Name><FuelTankCapacity unit="litres">61</FuelTankCapacity></Model><Model><Name>Hyundai Venue</Name><FuelTankCapacity unit="litres">63</FuelTankCapacity></Model><Model><Name>Hyundai Creta</Name><FuelTankCapacity unit="litres">42</FuelTankCapacity></Model><Model><Name>Hyundai Tucson</Name><FuelTankCapacity unit="litres">90</FuelTankCapacity></Model><Model><Name>Hyundai Santa Fe</Name><FuelTankCapacity unit="litres">89</FuelTankCapacity></Model><Model><Name>Hyundai Kona</Name><FuelTankCapacity unit="litres">87</FuelTankCapacity></Model><Model><Name>Hyundai Palisade</Name><FuelTankCapacity unit="litres">57</FuelTankCapacity></Model><Model><Name>Hyundai H-1</Name><FuelTankCapacity unit="litres">53</FuelTankCapacity></Model></Car><Car brand="Kia"><Model><Name>Kia Picanto</Name><FuelTankCapacity unit="litres">69</FuelTankCapacity></Model><Model><Name>Kia Rio</Name><FuelTankCapacity unit="litres">90</FuelTankCapacity></Model><Model><Name>Kia Cerato</Name><FuelTankCapacity unit="litres">55</FuelTankCapacity></Model><Model><Name>Kia Seltos</Name><FuelTankCapacity unit="litres">75</FuelTankCapacity></Model><Model><Name>Kia Sportage</Name><FuelTankCapacity unit="litres">86</FuelTankCapacity></Model><Model><Name>Kia Sorento</Name><FuelTankCapacity unit="litres">70</FuelTankCapacity></Model><Model><Name>Kia Sonet</Name><FuelTankCapacity unit="litres">90</FuelTankCapacity></Model><Model><Name>Kia Carnival</Name><FuelTankCapacity unit="litres">83</FuelTankCapacity></Model><Model><Name>Kia K2700</Name><FuelTankCapacity unit="litres">36</FuelTankCapacity></Model><Model><Name>Kia EV6</Name><FuelTankCapacity unit="litres">53</FuelTankCapacity></Model></Car><Car brand="Nissan"><Model><Name>Nissan Navara</Name><FuelTankCapacity unit="litres">42</FuelTankCapacity></Model><Model><Name>Nissan Magnite</Name><FuelTankCapacity unit="litres">56</FuelTankCapacity></Model><Model><Name>Nissan X-Trail</Name><FuelTankCapacity unit="litres">53</FuelTankCapacity></Model><Model><Name>Nissan Patrol</Name><FuelTankCapacity unit="litres">63</FuelTankCapacity></Model><Model><Name>Nissan Almera</Name><FuelTankCapacity unit="litres">62</FuelTankCapacity></Model><Model><Name>Nissan Qashqai</Name><FuelTankCapacity unit="litres">90</FuelTankCapacity></Model><Model><Name>Nissan NP200</Name><FuelTankCapacity unit="litres">49</FuelTankCapacity></Model><Model><Name>Nissan Leaf</Name><FuelTankCapacity unit="litres">81</FuelTankCapacity></Model><Model><Name>Nissan Murano</Name><FuelTankCapacity unit="litres">52</FuelTankCapacity></Model><Model><Name>Nissan Juke</Name><FuelTankCapacity unit="litres">79</FuelTankCapacity></Model></Car><Car brand="Renault"><Model><Name>Renault Kwid</Name><FuelTankCapacity unit="litres">60</FuelTankCapacity></Model><Model><Name>Renault Triber</Name><FuelTankCapacity unit="litres">44</FuelTankCapacity></Model><Model><Name>Renault Duster</Name><FuelTankCapacity unit="litres">38</FuelTankCapacity></Model><Model><Name>Renault Clio</Name><FuelTankCapacity unit="litres">42</FuelTankCapacity></Model><Model><Name>Renault Captur</Name><FuelTankCapacity unit="litres">42</FuelTankCapacity></Model><Model><Name>Renault Megane</Name><FuelTankCapacity unit="litres">49</FuelTankCapacity></Model><Model><Name>Renault Koleos</Name><FuelTankCapacity unit="litres">79</FuelTankCapacity></Model><Model><Name>Renault Sandero</Name><FuelTankCapacity unit="litres">67</FuelTankCapacity></Model><Model><Name>Renault Stepway</Name><FuelTankCapacity unit="litres">47</FuelTankCapacity></Model><Model><Name>Renault Logan</Name><FuelTankCapacity unit="litres">73</FuelTankCapacity></Model></Car><Car brand="BMW"><Model><Name>BMW 1 Series</Name><FuelTankCapacity unit="litres">90</FuelTankCapacity></Model><Model><Name>BMW 2 Series</Name><FuelTankCapacity unit="litres">50</FuelTankCapacity></Model><Model><Name>BMW 3 Series</Name><FuelTankCapacity unit="litres">46</FuelTankCapacity></Model><Model><Name>BMW 4 Series</Name><FuelTankCapacity unit="litres">61</FuelTankCapacity></Model><Model><Name>BMW 5 Series</Name><FuelTankCapacity unit="litres">42</FuelTankCapacity></Model><Model><Name>BMW 7 Series</Name><FuelTankCapacity unit="litres">72</FuelTankCapacity></Model><Model><Name>BMW X1</Name><FuelTankCapacity unit="litres">42</FuelTankCapacity></Model><Model><Name>BMW X3</Name><FuelTankCapacity unit="litres">83</FuelTankCapacity></Model><Model><Name>BMW X5</Name><FuelTankCapacity unit="litres">59</FuelTankCapacity></Model><Model><Name>BMW X7</Name><FuelTankCapacity unit="litres">61</FuelTankCapacity></Model></Car><Car brand="Mercedes-Benz"><Model><Name>Mercedes-Benz A-Class</Name><FuelTankCapacity unit="litres">39</FuelTankCapacity></Model><Model><Name>Mercedes-Benz B-Class</Name><FuelTankCapacity unit="litres">81</FuelTankCapacity></Model><Model><Name>Mercedes-Benz C-Class</Name><FuelTankCapacity unit="litres">64</FuelTankCapacity></Model><Model><Name>Mercedes-Benz E-Class</Name><FuelTankCapacity unit="litres">83</FuelTankCapacity></Model><Model><Name>Mercedes-Benz S-Class</Name><FuelTankCapacity unit="litres">77</FuelTankCapacity></Model><Model><Name>Mercedes-Benz GLA</Name><FuelTankCapacity unit="litres">48</FuelTankCapacity></Model><Model><Name>Mercedes-Benz GLB</Name><FuelTankCapacity unit="litres">75</FuelTankCapacity></Model><Model><Name>Mercedes-Benz GLC</Name><FuelTankCapacity unit="litres">89</FuelTankCapacity></Model><Model><Name>Mercedes-Benz GLE</Name><FuelTankCapacity unit="litres">58</FuelTankCapacity></Model><Model><Name>Mercedes-Benz GLS</Name><FuelTankCapacity unit="litres">65</FuelTankCapacity></Model></Car></CarsInSouthAfrica>